ma_algorithm/__init__.py
ma_algorithm/exponential_moving_average.py
ma_algorithm/simple_moving_average.py
ma_algorithm/simple_moving_average_with_lstm.py
ma_algorithm-2.1.0.dist-info/LICENSE
ma_algorithm-2.1.0.dist-info/METADATA
ma_algorithm-2.1.0.dist-info/WHEEL
ma_algorithm-2.1.0.dist-info/top_level.txt
ma_algorithm-2.1.0.dist-info/RECORD
